Workbook

Sheet 回测概要
A1: 项目 | B1: 结果
A2: 回测范围 | B2: 商品全市场五年：2021-08-02 ~ 2026-10-29（1269 个交易日）
A3: 开过仓的品种 | B3: 豆一、沪银、沪铝、氧化铝、沪金、豆二、沥青、玉米、棉花、玉米淀粉、沪铜、苯乙烯、乙二醇、玻璃、燃料油、热卷、铁矿石、鸡蛋、焦煤、塑料、碳酸锂、生猪、豆粕、甲醇、沪镍、菜油、棕榈油、聚丙烯、对二甲苯、螺纹钢、菜粕、纯碱、硅铁、烧碱、工业硅、锰硅、纸浆、白糖、PTA、尿素、PVC、豆油、沪锌
A4: 规则 | B4: v4.6 常胜将军打分 → 主表（大品种、≥4 分、无冲突/撤退/转向、≥2 个将军，多空各前 5）→ 跟踪台（按 ftrade/tracker.py 当前参数：v2.5 为顺 5 日线入场、3ATR 移动止损、不限时；¼凯利+星级上限、3% 硬止损、组合 10%/板块 6%/相关组 3%、次日开盘成交、转弱即平、凯利≤0 开 1% 影子仓）
A5: 本金（固定，不复利） | B5: 1,000,000
A6: 计入组合的成交笔数 | B6: 971
A7: 胜率 | B7: 52.8%
A8: 平均盈利 / 平均亏损 | B8: 7,470 / 6,852（盈亏比 1.09）
A9: 盈亏因子 | B9: 1.22
A10: 毛收益 | B10: 714,263（71.4%，年化约 10.9%）
A11: 估算成本（每边 1 跳滑点 + 手续费万 0.5） | B11: 278,004
A12: 净收益（扣成本） | B12: 436,259（43.6%，年化约 7.2%）
A13: 最大回撤（毛 / 净） | B13: 21.4% / 27.8%
A14: 影子仓（凯利≤0 时 1% 只统计） | B14: 1138 笔，合计 -91,887
A15: 说明 | B15: 纸面回测，不含研报/人工调分/宏观事件限额；席位只取持仓占品种 ≥3% 的合约前 20 名；换月按前一日持仓最大合约且只向后换。不是实盘建议。

Sheet 净值曲线
A1: 日期 | B1: 已实现 | C1: 浮动 | D1: 毛权益 | E1: 净权益(扣成本) | F1: 回撤%(毛) | G1: 持仓数 | H1: 风险占用%
A2: 2021-08-02 | B2: 0 | C2: 0 | D2: 1000000 | E2: 1000000 | F2: 0 | G2: 2 | H2: 2
A3: 2021-08-03 | B3: 1300 | C3: 0 | D3: 1001300 | E3: 1001133 | F3: 0 | G3: 2 | H3: 2
A4: 2021-08-04 | B4: 1300 | C4: -1200 | D4: 1000100 | E4: 999933 | F4: -0.12 | G4: 2 | H4: 2
A5: 2021-08-05 | B5: 2020 | C5: 800 | D5: 1002820 | E5: 1002450 | F5: 0 | G5: 1 | H5: 1
A6: 2021-08-06 | B6: 2160 | C6: 0 | D6: 1002160 | E6: 1001745 | F6: -0.07 | G6: 4 | H6: 4
A7: 2021-08-09 | B7: 2860 | C7: -3620 | D7: 999240 | E7: 998727 | F7: -0.36 | G7: 2 | H7: 2
A8: 2021-08-10 | B8: 2550 | C8: 0 | D8: 1002550 | E8: 1001912 | F8: -0.03 | G8: 2 | H8: 2
A9: 2021-08-11 | B9: 5330 | C9: -1500 | D9: 1003830 | E9: 1003143 | F9: 0 | G9: 2 | H9: 2
A10: 2021-08-12 | B10: 5370 | C10: -2070 | D10: 1003300 | E10: 1002564 | F10: -0.05 | G10: 2 | H10: 3
A11: 2021-08-13 | B11: 5370 | C11: -1700 | D11: 1003670 | E11: 1002934 | F11: -0.02 | G11: 2 | H11: 3
A12: 2021-08-16 | B12: 5090 | C12: -2820 | D12: 1002270 | E12: 1001499 | F12: -0.16 | G12: 4 | H12: 7
A13: 2021-08-17 | B13: 2770 | C13: 6300 | D13: 1009070 | E13: 1008117 | F13: 0 | G13: 6 | H13: 10
... A1270: 2026-10-29 | B1270: 693593 | C1270: 20670 | D1270: 1714263 | E1270: 1436259 | F1270: -0.58 | G1270: 4 | H1270: 10

Sheet 分组统计
A1: 按年份
A2: 分组 | B2: 笔数 | C2: 胜率% | D2: 均盈 | E2: 均亏 | F2: 盈亏比 | G2: 盈亏因子 | H2: 盈亏合计 | I2: 估算成本
A3: 2021 | B3: 73 | C3: 42.5 | D3: 2232 | E3: 4009 | F3: 0.56 | G3: 0.41 | H3: -99185 | I3: 8369
A4: 2022 | B4: 145 | C4: 50.3 | D4: 7638 | E4: 6546 | F4: 1.17 | G4: 1.18 | H4: 86309 | I4: 24621
A5: 2023 | B5: 177 | C5: 49.7 | D5: 7214 | E5: 8160 | F5: 0.88 | G5: 0.87 | H5: -91375 | I5: 43910
A6: 2024 | B6: 213 | C6: 56.8 | D6: 7151 | E6: 5332 | F6: 1.34 | G6: 1.76 | H6: 374729 | I6: 58135
A7: 2025 | B7: 200 | C7: 57.5 | D7: 8082 | E7: 7987 | F7: 1.01 | G7: 1.37 | H7: 250614 | I7: 84441
A8: 2026 | B8: 163 | C8: 52.1 | D8: 9123 | E8: 7730 | F8: 1.18 | G8: 1.29 | H8: 172501 | I8: 58528
A10: 按月份
A11: 分组 | B11: 笔数 | C11: 胜率% | D11: 均盈 | E11: 均亏 | F11: 盈亏比 | G11: 盈亏因子 | H11: 盈亏合计 | I11: 估算成本
A12: 2021-08 | B12: 23 | C12: 47.8 | D12: 2332 | E12: 1481 | F12: 1.57 | G12: 1.44 | H12: 7880 | I12: 2308
A13: 2021-09 | B13: 17 | C13: 35.3 | D13: 3537 | E13: 6206 | F13: 0.57 | G13: 0.31 | H13: -47051 | I13: 3812
A14: 2021-10 | B14: 10 | C14: 50 | D14: 2539 | E14: 5815 | F14: 0.44 | G14: 0.44 | H14: -16381 | I14: 854
A15: 2021-11 | B15: 14 | C15: 50 | D15: 957 | E15: 2556 | F15: 0.37 | G15: 0.37 | H15: -11194 | I15: 603
A16: 2021-12 | B16: 9 | C16: 22.2 | D16: 1460 | E16: 5051 | F16: 0.29 | G16: 0.08 | H16: -32439 | I16: 792
A17: 2022-01 | B17: 19 | C17: 63.2 | D17: 1608 | E17: 1786 | F17: 0.9 | G17: 1.54 | H17: 6785 | I17: 1452
A18: 2022-02 | B18: 14 | C18: 42.9 | D18: 6396 | E18: 7504 | F18: 0.85 | G18: 0.64 | H18: -21654 | I18: 2107
A19: 2022-03 | B19: 10 | C19: 70 | D19: 19012 | E19: 5840 | F19: 3.26 | G19: 7.6 | H19: 115565 | I19: 1438
A20: 2022-04 | B20: 11 | C20: 54.5 | D20: 9035 | E20: 8149 | F20: 1.11 | G20: 1.33 | H20: 13465 | I20: 1804
A21: 2022-05 | B21: 14 | C21: 50 | D21: 5801 | E21: 8097 | F21: 0.72 | G21: 0.72 | H21: -16075 | I21: 2835
A22: 2022-06 | B22: 10 | C22: 50 | D22: 6970 | E22: 8311 | F22: 0.84 | G22: 0.84 | H22: -6705 | I22: 2220
A23: 2022-07 | B23: 18 | C23: 38.9 | D23: 8686 | E23: 4569 | F23: 1.9 | G23: 1.21 | H23: 10537 | I23: 3079
... A74: 2026-10 | B74: 13 | C74: 69.2 | D74: 10349 | E74: 2605 | F74: 3.97 | G74: 8.94 | H74: 82721 | I74: 3985
A76: 按品种
A77: 分组 | B77: 笔数 | C77: 胜率% | D77: 均盈 | E77: 均亏 | F77: 盈亏比 | G77: 盈亏因子 | H77: 盈亏合计 | I77: 估算成本
A78: PTA(TA) | B78: 30 | C78: 50 | D78: 6600 | E78: 4284 | F78: 1.54 | G78: 1.54 | H78: 34740 | I78: 7134
A79: PVC(V) | B79: 41 | C79: 56.1 | D79: 7561 | E79: 4873 | F79: 1.55 | G79: 1.98 | H79: 86181 | I79: 7982
A80: 乙二醇(EG) | B80: 20 | C80: 35 | D80: 9206 | E80: 7775 | F80: 1.18 | G80: 0.64 | H80: -36629 | I80: 3482
A81: 塑料(L) | B81: 28 | C81: 64.3 | D81: 7397 | E81: 9172 | F81: 0.81 | G81: 1.45 | H81: 41415 | I81: 5804
A82: 对二甲苯(PX) | B82: 2 | C82: 0 | D82: 0 | E82: 8910 | F82: 0 | G82: 0 | H82: -17820 | I82: 521
A83: 尿素(UR) | B83: 11 | C83: 63.6 | D83: 3760 | E83: 3675 | F83: 1.02 | G83: 1.79 | H83: 11620 | I83: 4227
A84: 工业硅(SI) | B84: 21 | C84: 61.9 | D84: 8456 | E84: 3984 | F84: 2.12 | G84: 3.45 | H84: 78050 | I84: 9654
A85: 棉花(CF) | B85: 33 | C85: 48.5 | D85: 12895 | E85: 4586 | F85: 2.81 | G85: 2.65 | H85: 128366 | I85: 16471
A86: 棕榈油(P) | B86: 37 | C86: 45.9 | D86: 7334 | E86: 7962 | F86: 0.92 | G86: 0.78 | H86: -34558 | I86: 6224
A87: 氧化铝(AO) | B87: 4 | C87: 25 | D87: 440 | E87: 13671 | F87: 0.03 | G87: 0.01 | H87: -40574 | I87: 1446
A88: 沥青(BU) | B88: 27 | C88: 44.4 | D88: 8057 | E88: 8797 | F88: 0.92 | G88: 0.73 | H88: -35273 | I88: 5160
A89: 沪金(AU) | B89: 30 | C89: 60 | D89: 7612 | E89: 6696 | F89: 1.14 | G89: 1.71 | H89: 56660 | I89: 3829
... A120: 鸡蛋(JD) | B120: 8 | C120: 62.5 | D120: 2848 | E120: 1773 | F120: 1.61 | G120: 2.68 | H120: 8920 | I120: 1681
A122: 按板块
A123: 分组 | B123: 笔数 | C123: 胜率% | D123: 均盈 | E123: 均亏 | F123: 盈亏比 | G123: 盈亏因子 | H123: 盈亏合计 | I123: 估算成本
A124: 农产品 | B124: 217 | C124: 56.2 | D124: 7975 | E124: 8226 | F124: 0.97 | G124: 1.24 | H124: 191406 | I124: 70147
A125: 化工 | B125: 191 | C125: 53.9 | D125: 6714 | E125: 6453 | F125: 1.04 | G125: 1.22 | H125: 123671 | I125: 42126
A126: 建材 | B126: 98 | C126: 53.1 | D126: 5824 | E126: 7017 | F126: 0.83 | G126: 0.94 | H126: -19932 | I126: 42414
A127: 有色 | B127: 173 | C127: 53.2 | D127: 7322 | E127: 5184 | F127: 1.41 | G127: 1.6 | H127: 253639 | I127: 40672
A128: 能源 | B128: 47 | C128: 51.1 | D128: 10818 | E128: 8682 | F128: 1.25 | G128: 1.3 | H128: 59938 | I128: 9463
A129: 贵金属 | B129: 69 | C129: 56.5 | D129: 7315 | E129: 5211 | F129: 1.4 | G129: 1.82 | H129: 128945 | I129: 9124
A130: 软商品 | B130: 56 | C130: 42.9 | D130: 10868 | E130: 6456 | F130: 1.68 | G130: 1.26 | H130: 54239 | I130: 24822
A131: 黑色 | B131: 120 | C131: 47.5 | D131: 6760 | E131: 7677 | F131: 0.88 | G131: 0.8 | H131: -98313 | I131: 39236
A133: 按方向
A134: 分组 | B134: 笔数 | C134: 胜率% | D134: 均盈 | E134: 均亏 | F134: 盈亏比 | G134: 盈亏因子 | H134: 盈亏合计 | I134: 估算成本
A135: 多 | B135: 499 | C135: 53.7 | D135: 8108 | E135: 6523 | F135: 1.24 | G135: 1.44 | H135: 666127 | I135: 119216
A136: 空 | B136: 472 | C136: 51.9 | D136: 6771 | E136: 7187 | F136: 0.94 | G136: 1.02 | H136: 27466 | I136: 158788
A138: 按星级
A139: 分组 | B139: 笔数 | C139: 胜率% | D139: 均盈 | E139: 均亏 | F139: 盈亏比 | G139: 盈亏因子 | H139: 盈亏合计 | I139: 估算成本
A140: 2星 | B140: 33 | C140: 39.4 | D140: 1778 | E140: 4766 | F140: 0.37 | G140: 0.24 | H140: -72210 | I140: 3019
A141: 3星 | B141: 938 | C141: 53.3 | D141: 7618 | E141: 6947 | F141: 1.1 | G141: 1.25 | H141: 765803 | I141: 274985
A143: 按平仓原因
A144: 分组 | B144: 笔数 | C144: 胜率% | D144: 均盈 | E144: 均亏 | F144: 盈亏比 | G144: 盈亏因子 | H144: 盈亏合计 | I144: 估算成本
A145: 反向信号 | B145: 18 | C145: 27.8 | D145: 6292 | E145: 9546 | F145: 0.66 | G145: 0.25 | H145: -92640 | I145: 6719
A146: 大将军转向 | B146: 342 | C146: 53.8 | D146: 7331 | E146: 4048 | F146: 1.81 | G146: 2.11 | H146: 709310 | I146: 95052
A147: 将军撤退 | B147: 314 | C147: 66.6 | D147: 6730 | E147: 3392 | F147: 1.98 | G147: 3.95 | H147: 1050530 | I147: 88612
A148: 将军撤退+大将军转向 | B148: 176 | C148: 60.2 | D148: 9068 | E148: 4750 | F148: 1.91 | G148: 2.89 | H148: 628650 | I148: 50233
A149: 强平(浮亏≥3%) | B149: 1 | C149: 0 | D149: 0 | E149: 34200 | F149: 0 | G149: 0 | H149: -34200 | I149: 188
A150: 止损 | B150: 107 | C150: 8.4 | D150: 9311 | E150: 15043 | F150: 0.62 | G150: 0.06 | H150: -1390377 | I150: 34513
A151: 跳空止损 | B151: 13 | C151: 0 | D151: 0 | E151: 13668 | F151: 0 | G151: 0 | H151: -177680 | I151: 2687

Sheet 月度盈亏
A1: 月份 | B1: 月度盈亏(毛)
A2: 2021-08 | B2: 6720
A3: 2021-09 | B3: -52071
A4: 2021-10 | B4: -10201
A5: 2021-11 | B5: -16644
A6: 2021-12 | B6: -26989
A7: 2022-01 | B7: 3065
A8: 2022-02 | B8: 5746
A9: 2022-03 | B9: 82575
A10: 2022-04 | B10: 34250
A11: 2022-05 | B11: -28130
A12: 2022-06 | B12: -7295
A13: 2022-07 | B13: -12743
... A64: 2026-10 | B64: 107951

Sheet 参数
A1: 期货信号跟踪台 · 2026-10-29 回测
A3: 账户资金（元） | B3: 1000000 | C3: 纸面账户规模
A4: 组合计划风险上限 | B4: 0.1 | C4: 所有实盘持仓风险预算占比合计上限
A5: 单品种风险上限 | B5: 0.03 | C5: 单品种最大亏损不超过总资金 3%（硬止损）
A6: 同板块同方向上限 | B6: 0.06 | C6: 同一板块同一方向风险预算合计上限
A7: 技术止损倍数（ATR） | B7: 3 | C7: 入场价 ∓ 3×ATR(14)，之后按 3×ATR 移动
A8: 保证金比例（估算） | B8: 0.12 | C8: 假设值，按实际开户比例修改
A9: 相关同组上限 | B9: 0.03 | C9: 同方向、40 日相关 ≥0.8 的品种合计上限
A12: 规则（跟踪台 v2.5）
A13: 手数 = 向下取整(风险预算 ÷ (3×ATR×合约乘数))；计划风险 = |入场−止损|×手数×乘数。
A14: 风险预算% = min(¼凯利, 样本分档上限, 星级上限)：已平<10笔固定1%；10–29笔≤2%；≥30笔≤3%；3星≤3%、2星≤2%、1星只开观察仓。
A15: 组合 ≤10%；同板块同方向 ≤6%；高相关同组 ≤3%；一级宏观事件前单方向 ≤7%。
A16: 入场：收盘信号次日开盘（夜盘第一笔）成交记账；“待成交”的入场价暂为信号日收盘价。
A17: 入场须顺 5 日线（逆势观望）；止损按 3×ATR 移动，不限持有天数（最长 60 日）；同向信号=续持；反向先平后开；将军撤退/大将军转向当天收盘平。
A18: 蓝色=输入值可改；黑色=公式；绿色=引用参数页。仅供参考，不构成投资建议。
A20: 宏观：回测（商品全市场五年 2021-08-02 ~ 2026-10-29）

Sheet 今日建议
A1: 品种 | B1: 代码 | C1: 方向 | D1: 星级 | E1: 动作 | F1: 手数 | G1: 入场价 | H1: 技术止损 | I1: 合约乘数 | J1: 风险预算占比 | K1: 计划风险（元） | L1: 占资金 | M1: 合约货值（元） | N1: 仓位依据 / 不做原因 | O1: 理由
A2: 碳酸锂 | B2: LC | C2: 空 | D2: ★★★ | E2: 续持 | F2: 1 | G2: 96200 | H2: 106727.14 | I2: 1 | J2: 0.03 | K2: =IF(F2="","",ABS(G2-H2)*F2*I2) | L2: =IF(K2="","",K2/参数!$B$3) | M2: =IF(F2="","",G2*F2*I2) | N2: 续持原仓（2026-10-26开） | O2: 将军净-13.2%，4个将军
A3: 热卷 | B3: HC | C3: 空 | D3: ★★ | E3: 观望 | G3: 3192 | I3: 10 | K3: =IF(F3="","",ABS(G3-H3)*F3*I3) | L3: =IF(K3="","",K3/参数!$B$3) | M3: =IF(F3="","",G3*F3*I3) | N3: 逆5日线（收盘在5日线上，不追空） | O3: 将军净-7.8%，4个将军
A4: 纸浆 | B4: SP | C4: 空 | D4: ★★ | E4: 观望 | G4: 4604 | I4: 10 | K4: =IF(F4="","",ABS(G4-H4)*F4*I4) | L4: =IF(K4="","",K4/参数!$B$3) | M4: =IF(F4="","",G4*F4*I4) | N4: 逆5日线（收盘在5日线上，不追空） | O4: 将军净-20.1%，4个将军
A5: 沪银 | B5: AG | C5: 空 | D5: ★★★ | E5: 不做 | G5: 12682 | I5: 15 | K5: =IF(F5="","",ABS(G5-H5)*F5*I5) | L5: =IF(K5="","",K5/参数!$B$3) | M5: =IF(F5="","",G5*F5*I5) | N5: 组合风险已近10%，预算缩小 | O5: 将军净-17.8%，4个将军
A6: 豆粕 | B6: M | C6: 空 | D6: ★★★ | E6: 不做 | G6: 3161 | I6: 10 | K6: =IF(F6="","",ABS(G6-H6)*F6*I6) | L6: =IF(K6="","",K6/参数!$B$3) | M6: =IF(F6="","",G6*F6*I6) | N6: 组合风险已近10%，预算缩小 | O6: 将军净-12.6%，4个将军
A7: PVC | B7: V | C7: 多 | D7: ★★★ | E7: 不做 | G7: 5299 | I7: 5 | K7: =IF(F7="","",ABS(G7-H7)*F7*I7) | L7: =IF(K7="","",K7/参数!$B$3) | M7: =IF(F7="","",G7*F7*I7) | N7: 组合风险已近10%，预算缩小 | O7: 将军净9.3%，4个将军
A8: 尿素 | B8: UR | C8: 多 | D8: ★★ | E8: 影子仓 | F8: 7 | G8: 1716 | H8: 1647 | I8: 20 | J8: 0.01 | K8: =IF(F8="","",ABS(G8-H8)*F8*I8) | L8: =IF(K8="","",K8/参数!$B$3) | M8: =IF(F8="","",G8*F8*I8) | N8: 凯利≤0，开1%影子仓（只统计，不计入组合） | O8: 将军净5.2%，4个将军
I9: 合计（不含观察仓） | J9: =SUMIFS(J2:J8,$E$2:$E$8,"<>观察仓",$E$2:$E$8,"<>不做") | K9: =SUMIFS(K2:K8,$E$2:$E$8,"<>观察仓",$E$2:$E$8,"<>不做") | L9: =SUMIFS(L2:L8,$E$2:$E$8,"<>观察仓",$E$2:$E$8,"<>不做") | M9: =SUMIFS(M2:M8,$E$2:$E$8,"<>观察仓",$E$2:$E$8,"<>不做")

Sheet 当前持仓
A1: 开仓日 | B1: 品种 | C1: 代码 | D1: 方向 | E1: 星级 | F1: 板块 | G1: 状态 | H1: 手数 | I1: 入场价 | J1: 技术止损 | K1: 合约乘数 | L1: 最新收盘 | M1: 风险预算占比 | N1: 计划风险（元） | O1: 浮动盈亏（元） | P1: R倍数 | Q1: 合约货值（元） | R1: 保证金估算（元） | S1: 已持天数 | T1: 观察仓
A2: 2026-10-08 | B2: 玻璃 | C2: FG | D2: 空 | E2: ★★★ | F2: 建材 | G2: 持有 | H2: 22 | I2: 867 | J2: 872.5 | K2: 20 | L2: 857 | M2: 0.03 | N2: =ABS(I2-J2)*H2*K2 | O2: =IF(D2="多",1,-1)*(L2-I2)*H2*K2 | P2: =O2/(M2*参数!$B$3) | Q2: =L2*H2*K2 | R2: =Q2*参数!$B$8 | S2: 15 | T2: 否
A3: 2026-10-21 | B3: 纸浆 | C3: SP | D3: 空 | E3: ★★★ | F3: 软商品 | G3: 持有 | H3: 14 | I3: 4676 | J3: 4710.86 | K3: 10 | L3: 4604 | M3: 0.03 | N3: =ABS(I3-J3)*H3*K3 | O3: =IF(D3="多",1,-1)*(L3-I3)*H3*K3 | P3: =O3/(M3*参数!$B$3) | Q3: =L3*H3*K3 | R3: =Q3*参数!$B$8 | S3: 1 | T3: 否
A4: 2026-10-26 | B4: 碳酸锂 | C4: LC | D4: 空 | E4: ★★★ | F4: 有色 | G4: 持有 | H4: 1 | I4: 96200 | J4: 106727.14 | K4: 1 | L4: 88360 | M4: 0.03 | N4: =ABS(I4-J4)*H4*K4 | O4: =IF(D4="多",1,-1)*(L4-I4)*H4*K4 | P4: =O4/(M4*参数!$B$3) | Q4: =L4*H4*K4 | R4: =Q4*参数!$B$8 | S4: 0 | T4: 否
A5: 2026-10-27 | B5: 热卷 | C5: HC | D5: 空 | E5: ★★★ | F5: 黑色 | G5: 持有 | H5: 11 | I5: 3177 | J5: 3245.14 | K5: 10 | L5: 3192 | M5: 0.01 | N5: =ABS(I5-J5)*H5*K5 | O5: =IF(D5="多",1,-1)*(L5-I5)*H5*K5 | P5: =O5/(M5*参数!$B$3) | Q5: =L5*H5*K5 | R5: =Q5*参数!$B$8 | S5: 1 | T5: 否
A6: 2026-09-29 | B6: PTA | C6: TA | D6: 多 | E6: ★★ | F6: 化工 | G6: 观察仓 | H6: 3 | I6: 6250 | J6: 6266 | K6: 5 | L6: 6648 | M6: 0.01 | N6: =ABS(I6-J6)*H6*K6 | O6: =IF(D6="多",1,-1)*(L6-I6)*H6*K6 | P6: =O6/(M6*参数!$B$3) | Q6: =L6*H6*K6 | R6: =Q6*参数!$B$8 | S6: 17 | T6: 是
A7: 2026-10-16 | B7: 硅铁 | C7: SF | D7: 空 | E7: ★★ | F7: 黑色 | G7: 观察仓 | H7: 7 | I7: 5870 | J7: 6031.86 | K7: 5 | L7: 5836 | M7: 0.01 | N7: =ABS(I7-J7)*H7*K7 | O7: =IF(D7="多",1,-1)*(L7-I7)*H7*K7 | P7: =O7/(M7*参数!$B$3) | Q7: =L7*H7*K7 | R7: =Q7*参数!$B$8 | S7: 9 | T7: 是
A8: 2026-10-27 | B8: 沪镍 | C8: NI | D8: 空 | E8: ★★ | F8: 有色 | G8: 观察仓 | H8: 1 | I8: 118130 | J8: 123498.57 | K8: 1 | L8: 118090 | M8: 0.01 | N8: =ABS(I8-J8)*H8*K8 | O8: =IF(D8="多",1,-1)*(L8-I8)*H8*K8 | P8: =O8/(M8*参数!$B$3) | Q8: =L8*H8*K8 | R8: =Q8*参数!$B$8 | S8: 1 | T8: 是
A9: 2026-10-27 | B9: 氧化铝 | C9: AO | D9: 空 | E9: ★★ | F9: 有色 | G9: 观察仓 | H9: 3 | I9: 2563 | J9: 2688.07 | K9: 20 | L9: 2595 | M9: 0.01 | N9: =ABS(I9-J9)*H9*K9 | O9: =IF(D9="多",1,-1)*(L9-I9)*H9*K9 | P9: =O9/(M9*参数!$B$3) | Q9: =L9*H9*K9 | R9: =Q9*参数!$B$8 | S9: 2 | T9: 是
A10: 2026-10-29 | B10: 尿素 | C10: UR | D10: 多 | E10: ★★ | F10: 建材 | G10: 待成交 | H10: 7 | I10: 1716 | J10: 1647 | K10: 20 | L10: 1716 | M10: 0.01 | N10: =ABS(I10-J10)*H10*K10 | O10: =IF(D10="多",1,-1)*(L10-I10)*H10*K10 | P10: =O10/(M10*参数!$B$3) | Q10: =L10*H10*K10 | R10: =Q10*参数!$B$8 | S10: 0 | T10: 是
L11: 合计（实盘） | M11: =SUMIF($T$2:$T$10,"否",M2:M10) | N11: =SUMIF($T$2:$T$10,"否",N2:N10) | O11: =SUMIF($T$2:$T$10,"否",O2:O10) | Q11: =SUMIF($T$2:$T$10,"否",Q2:Q10) | R11: =SUMIF($T$2:$T$10,"否",R2:R10)
L12: 组合上限 | M12: =参数!$B$4
L13: 剩余空间 | M13: =M12-M11
L14: 空单风险预算 | M14: =SUMIFS(M2:M10,D2:D10,"空",T2:T10,"否")
L15: 多单风险预算 | M15: =SUMIFS(M2:M10,D2:D10,"多",T2:T10,"否")
L16: 货值杠杆（倍） | Q16: =Q11/参数!$B$3
L17: 保证金占资金 | R17: =R11/参数!$B$3
A20: 板块风险（实盘，按方向）
A21: 板块 | B21: 方向 | C21: 风险预算占比 | D21: 计划风险（元）
A22: 建材 | B22: 空 | C22: =SUMIFS($M$2:$M$10,$F$2:$F$10,A22,$D$2:$D$10,B22,$T$2:$T$10,"否") | D22: =SUMIFS($N$2:$N$10,$F$2:$F$10,A22,$D$2:$D$10,B22,$T$2:$T$10,"否")
A23: 有色 | B23: 空 | C23: =SUMIFS($M$2:$M$10,$F$2:$F$10,A23,$D$2:$D$10,B23,$T$2:$T$10,"否") | D23: =SUMIFS($N$2:$N$10,$F$2:$F$10,A23,$D$2:$D$10,B23,$T$2:$T$10,"否")
A24: 软商品 | B24: 空 | C24: =SUMIFS($M$2:$M$10,$F$2:$F$10,A24,$D$2:$D$10,B24,$T$2:$T$10,"否") | D24: =SUMIFS($N$2:$N$10,$F$2:$F$10,A24,$D$2:$D$10,B24,$T$2:$T$10,"否")
A25: 黑色 | B25: 空 | C25: =SUMIFS($M$2:$M$10,$F$2:$F$10,A25,$D$2:$D$10,B25,$T$2:$T$10,"否") | D25: =SUMIFS($N$2:$N$10,$F$2:$F$10,A25,$D$2:$D$10,B25,$T$2:$T$10,"否")
A27: R倍数 = 浮动盈亏 ÷ 风险预算。“待成交”行的入场价是信号日收盘价，次日按开盘价成交后更新。保证金按参数页比例粗估。

Sheet 当日平仓
A1: 开仓日 | B1: 平仓日 | C1: 品种 | D1: 代码 | E1: 方向 | F1: 星级 | G1: 手数 | H1: 入场价 | I1: 平仓价 | J1: 合约乘数 | K1: 风险预算（元） | L1: 盈亏（元） | M1: R倍数 | N1: 平仓原因 | O1: 观察仓
A2: 2026-10-28 | B2: 2026-10-29 | C2: 沥青 | D2: BU | E2: 多 | F2: ★★ | G2: 1 | H2: 5097 | I2: 5110 | J2: 10 | K2: 10000 | L2: =IF(E2="多",1,-1)*(I2-H2)*G2*J2 | M2: =L2/K2 | N2: 将军撤退+大将军转向 | O2: 是
A3: 2026-10-21 | B3: 2026-10-29 | C3: 棕榈油 | D3: P | E3: 多 | F3: ★★ | G3: 1 | H3: 9610 | I3: 9177.36 | J3: 10 | K3: 10000 | L3: =IF(E3="多",1,-1)*(I3-H3)*G3*J3 | M3: =L3/K3 | N3: 止损 | O3: 是
K4: 合计（实盘） | L4: =SUMIF(O2:O3,"否",L2:L3)

Sheet 已平记录
A1: 开仓日 | B1: 平仓日 | C1: 品种 | D1: 代码 | E1: 方向 | F1: 星级 | G1: 手数 | H1: 入场价 | I1: 平仓价 | J1: 合约乘数 | K1: 风险预算（元） | L1: 盈亏（元） | M1: R倍数 | N1: 平仓原因 | O1: 观察仓
A2: 2026-10-28 | B2: 2026-10-29 | C2: 沥青 | D2: BU | E2: 多 | F2: ★★ | G2: 1 | H2: 5097 | I2: 5110 | J2: 10 | K2: 10000 | L2: =IF(E2="多",1,-1)*(I2-H2)*G2*J2 | M2: =L2/K2 | N2: 将军撤退+大将军转向 | O2: 是
A3: 2026-10-21 | B3: 2026-10-29 | C3: 棕榈油 | D3: P | E3: 多 | F3: ★★ | G3: 1 | H3: 9610 | I3: 9177.36 | J3: 10 | K3: 10000 | L3: =IF(E3="多",1,-1)*(I3-H3)*G3*J3 | M3: =L3/K3 | N3: 止损 | O3: 是
A4: 2026-10-27 | B4: 2026-10-28 | C4: 沪铝 | D4: AL | E4: 多 | F4: ★★ | G4: 2 | H4: 23585 | I4: 23540 | J4: 5 | K4: 10000 | L4: =IF(E4="多",1,-1)*(I4-H4)*G4*J4 | M4: =L4/K4 | N4: 将军撤退 | O4: 是
A5: 2026-10-26 | B5: 2026-10-28 | C5: PVC | D5: V | E5: 多 | F5: ★★ | G5: 5 | H5: 5134 | I5: 5267 | J5: 5 | K5: 10000 | L5: =IF(E5="多",1,-1)*(I5-H5)*G5*J5 | M5: =L5/K5 | N5: 将军撤退 | O5: 是
A6: 2026-10-23 | B6: 2026-10-28 | C6: 玉米 | D6: C | E6: 多 | F6: ★★ | G6: 15 | H6: 2212 | I6: 2224 | J6: 10 | K6: 10000 | L6: =IF(E6="多",1,-1)*(I6-H6)*G6*J6 | M6: =L6/K6 | N6: 将军撤退 | O6: 是
A7: 2026-10-19 | B7: 2026-10-28 | C7: 沥青 | D7: BU | E7: 空 | F7: ★★ | G7: 1 | H7: 4424 | I7: 5022.93 | J7: 10 | K7: 10000 | L7: =IF(E7="多",1,-1)*(I7-H7)*G7*J7 | M7: =L7/K7 | N7: 止损 | O7: 是
A8: 2026-09-30 | B8: 2026-10-28 | C8: 乙二醇 | D8: EG | E8: 多 | F8: ★★ | G8: 1 | H8: 4943 | I8: 5258 | J8: 10 | K8: 10000 | L8: =IF(E8="多",1,-1)*(I8-H8)*G8*J8 | M8: =L8/K8 | N8: 大将军转向 | O8: 是
A9: 2026-10-26 | B9: 2026-10-27 | C9: 螺纹钢 | D9: RB | E9: 空 | F9: ★★★ | G9: 12 | H9: 3036 | I9: 3040 | J9: 10 | K9: 10000 | L9: =IF(E9="多",1,-1)*(I9-H9)*G9*J9 | M9: =L9/K9 | N9: 将军撤退+大将军转向 | O9: 否
A10: 2026-10-22 | B10: 2026-10-26 | C10: 鸡蛋 | D10: JD | E10: 空 | F10: ★★ | G10: 3 | H10: 3240 | I10: 3305 | J10: 10 | K10: 10000 | L10: =IF(E10="多",1,-1)*(I10-H10)*G10*J10 | M10: =L10/K10 | N10: 将军撤退 | O10: 是
A11: 2026-10-22 | B11: 2026-10-26 | C11: 燃料油 | D11: FU | E11: 多 | F11: ★★★ | G11: 1 | H11: 4947 | I11: 5295 | J11: 10 | K11: 10000 | L11: =IF(E11="多",1,-1)*(I11-H11)*G11*J11 | M11: =L11/K11 | N11: 将军撤退 | O11: 否
A12: 2026-10-22 | B12: 2026-10-26 | C12: 豆一 | D12: A | E12: 多 | F12: ★★★ | G12: 3 | H12: 5450 | I12: 5379 | J12: 10 | K12: 10000 | L12: =IF(E12="多",1,-1)*(I12-H12)*G12*J12 | M12: =L12/K12 | N12: 大将军转向 | O12: 是
A13: 2026-10-14 | B13: 2026-10-26 | C13: 沪银 | D13: AG | E13: 空 | F13: ★★★ | G13: 1 | H13: 14000 | I13: 13040 | J13: 15 | K13: 30000 | L13: =IF(E13="多",1,-1)*(I13-H13)*G13*J13 | M13: =L13/K13 | N13: 将军撤退+大将军转向 | O13: 否
... A2110: 2021-08-02 | B2110: 2021-08-03 | C2110: 沪银 | D2110: AG | E2110: 多 | F2110: ★★ | G2110: 2 | H2110: 5366 | I2110: 5340 | J2110: 15 | K2110: 10000 | L2110: =IF(E2110="多",1,-1)*(I2110-H2110)*G2110*J2110 | M2110: =L2110/K2110 | N2110: 大将军转向 | O2110: 否
K2111: 合计（实盘） | L2111: =SUMIF(O2:O2110,"否",L2:L2110)

Sheet 凯利统计
A1: ¼ 凯利仓位计算（2 星及以上已平仓，按 R 倍数）
A2: # | B2: 交易 | C2: 星级 | D2: R倍数
A3: 1 | B3: 沪银多 08-02 | C3: 2 | D3: -0.08 | F3: 已平笔数 n | G3: =COUNT(D3:D2111)
A4: 2 | B4: 甲醇空 08-02 | C4: 2 | D4: 0.21 | F4: 盈利笔数 | G4: =COUNTIF(D3:D2111,">0")
A5: 3 | B5: 玉米多 08-03 | C5: 2 | D5: 0.07 | F5: 胜率 p | G5: =IF(G3=0,0,G4/G3)
A6: 4 | B6: 玻璃空 08-03 | C6: 2 | D6: 0.01 | F6: 平均盈利 R | G6: =IFERROR(AVERAGEIF(D3:D2111,">0"),0)
A7: 5 | B7: 棕榈油多 08-06 | C7: 3 | D7: 0 | F7: 平均亏损 R | G7: =IFERROR(-AVERAGEIF(D3:D2111,"<=0"),0)
A8: 6 | B8: 豆油多 08-06 | C8: 2 | D8: 0.07 | F8: 盈亏比 b | G8: =IF(G7=0,0,G6/G7)
A9: 7 | B9: 聚丙烯多 08-06 | C9: 3 | D9: 0.16 | F9: 凯利 f* = p−(1−p)/b | G9: =IF(G8=0,G5,G5-(1-G5)/G8)
A10: 8 | B10: PTA多 08-06 | C10: 3 | D10: -0.19 | F10: ¼ 凯利 | G10: =G9/4
A11: 9 | B11: 豆油多 08-10 | C11: 3 | D11: 0.28 | F11: 样本分档上限 | G11: =IF(G3<10,0.01,IF(G3<30,0.02,参数!$B$5))
A12: 10 | B12: 棕榈油多 08-11 | C12: 3 | D12: 0 | F12: 3 星上限 | G12: 0.03
A13: 11 | B13: 沪镍多 08-12 | C13: 2 | D13: -0.01 | F13: 2 星上限 | G13: 0.02
A14: 12 | B14: 纯碱多 08-16 | C14: 2 | D14: -0.12 | F14: 3 星建议风险 | G14: =IF(G3<10,0.01,IF(G9<=0,0,MIN(G10,G11,G12)))
A15: 13 | B15: 棕榈油多 08-17 | C15: 3 | D15: -0.19 | F15: 2 星建议风险 | G15: =IF(G3<10,0.01,IF(G9<=0,0,MIN(G10,G11,G13)))
A16: 14 | B16: 豆油多 08-17 | C16: 3 | D16: -0.14
A17: 15 | B17: 沪银空 08-10 | C17: 2 | D17: -0.04 | F17: 不含 1 星观察仓（含凯利≤0 时的影子仓）。星级分组不足 10 笔时，跟踪台借用 2 星及以上合并统计。
A18: 16 | B18: 棉花多 08-16 | C18: 3 | D18: 0.17
A19: 17 | B19: 沪镍空 08-19 | C19: 2 | D19: -0.08
A20: 18 | B20: PVC多 08-16 | C20: 3 | D20: 0.26
A21: 19 | B21: 甲醇多 08-23 | C21: 2 | D21: -0.39
A22: 20 | B22: 沪铝多 08-17 | C22: 3 | D22: 0.14
A23: 21 | B23: 纯碱多 08-20 | C23: 3 | D23: -0.02
A24: 22 | B24: 螺纹钢多 08-24 | C24: 2 | D24: -0.01
A25: 23 | B25: 聚丙烯空 08-19 | C25: 2 | D25: 0.31
A26: 24 | B26: 棕榈油多 08-24 | C26: 3 | D26: 0.1
A27: 25 | B27: PVC多 08-25 | C27: 3 | D27: 0
A28: 26 | B28: 甲醇多 09-02 | C28: 2 | D28: 0.03
A29: 27 | B29: PTA空 09-02 | C29: 3 | D29: -0.25
... A2111: 2109 | B2111: 沥青多 10-28 | C2111: 2 | D2111: 0.01

Sheet 每日信号台
A1: 日期 | B1: 品种 | C1: 方向 | D1: 星级 | E1: 分数 | F1: 动作 | G1: 手数 | H1: 收盘 | I1: 止损 | J1: 预算% | K1: 仓位规则/原因
A2: 2021-08-02 | B2: 沪银 | C2: 多 | D2: 2 | E2: 5 | F2: 开仓 | G2: 2 | H2: 5386 | I2: 5110.64 | J2: 1 | K2: 样本<10，固定1%
A3: 2021-08-02 | B3: 棉花 | C3: 多 | D3: 2 | E3: 5 | F3: 观望 | G3: 1 | H3: 17305 | I3: 16267.86 | J3: 1 | K3: 逆5日线（收盘在5日线下，不追多）
A4: 2021-08-02 | B4: 甲醇 | C4: 空 | D4: 2 | E4: 5 | F4: 开仓 | G4: 4 | H4: 2683 | I4: 2893 | J4: 1 | K4: 样本<10，固定1%
A5: 2021-08-03 | B5: 玻璃 | C5: 空 | D5: 2 | E5: 5 | F5: 开仓 | G5: 1 | H5: 2725 | I5: 2997.79 | J5: 1 | K5: 样本<10，固定1%
A6: 2021-08-03 | B6: 棉花 | C6: 多 | D6: 2 | E6: 4 | F6: 观望 | G6: 1 | H6: 17055 | I6: 16023.21 | J6: 1 | K6: 逆5日线（收盘在5日线下，不追多）
A7: 2021-08-03 | B7: 玉米 | C7: 多 | D7: 2 | E7: 4 | F7: 开仓 | G7: 9 | H7: 2607 | I7: 2506.5 | J7: 1 | K7: 样本<10，固定1%
A8: 2021-08-04 | B8: 棉花 | C8: 多 | D8: 3 | E8: 7 | F8: 观望 | G8: 1 | H8: 17245 | I8: 16198.21 | J8: 1 | K8: 逆5日线（收盘在5日线下，不追多）
A9: 2021-08-05 | B9: 聚丙烯 | C9: 多 | D9: 2 | E9: 4 | F9: 观望 | G9: 4 | H9: 8307 | I9: 7842.86 | J9: 1 | K9: 逆5日线（收盘在5日线下，不追多）
A10: 2021-08-06 | B10: 棕榈油 | C10: 多 | D10: 3 | E10: 7 | F10: 开仓 | G10: 1 | H10: 8486 | I10: 7763.86 | J10: 1 | K10: 样本<10，固定1%
A11: 2021-08-06 | B11: 焦煤 | C11: 多 | D11: 3 | E11: 6 | F11: 不做 | H11: 2374.5 | J11: 1 | K11: 1手风险13031元超过预算10000元
A12: 2021-08-06 | B12: PTA | C12: 多 | D12: 3 | E12: 6 | F12: 开仓 | G12: 3 | H12: 5404 | I12: 4845.14 | J12: 1 | K12: 样本<10，固定1%
A13: 2021-08-06 | B13: 聚丙烯 | C13: 多 | D13: 3 | E13: 6 | F13: 开仓 | G13: 4 | H13: 8359 | I13: 7916.71 | J13: 1 | K13: 样本<10，固定1%
A14: 2021-08-06 | B14: 豆油 | C14: 多 | D14: 2 | E14: 5 | F14: 开仓 | G14: 1 | H14: 8906 | I14: 8311.14 | J14: 1 | K14: 样本<10，固定1%
A15: 2021-08-10 | B15: 豆油 | C15: 多 | D15: 3 | E15: 7 | F15: 开仓 | G15: 1 | H15: 9040 | I15: 8470 | J15: 1 | K15: 样本<10，固定1%
A16: 2021-08-10 | B16: 沪银 | C16: 空 | D16: 2 | E16: 5 | F16: 开仓 | G16: 2 | H16: 5077 | I16: 5387.07 | J16: 1 | K16: 样本<10，固定1%
A17: 2021-08-10 | B17: 沪金 | C17: 空 | D17: 2 | E17: 4 | F17: 不做 | H17: 363.92 | J17: 1 | K17: 1手风险12857元超过预算10000元
A18: 2021-08-11 | B18: 棕榈油 | C18: 多 | D18: 3 | E18: 7 | F18: 开仓 | G18: 1 | H18: 8994 | I18: 8218.29 | J18: 1 | K18: 样本<10，固定1%
A19: 2021-08-12 | B19: 焦煤 | C19: 多 | D19: 2 | E19: 4 | F19: 观望 | G19: 1 | H19: 2205.5 | I19: 1976.11 | J19: 2 | K19: 逆5日线（收盘在5日线下，不追多）
A20: 2021-08-12 | B20: 聚丙烯 | C20: 空 | D20: 2 | E20: 4 | F20: 观望 | G20: 9 | H20: 8537 | I20: 8968.14 | J20: 2 | K20: 逆5日线（收盘在5日线上，不追空）
A21: 2021-08-12 | B21: 沪镍 | C21: 多 | D21: 2 | E21: 4 | F21: 开仓 | G21: 1 | H21: 146720 | I21: 135540.71 | J21: 2 | K21: ¼凯利超上限，取2%
A22: 2021-08-16 | B22: 纯碱 | C22: 多 | D22: 2 | E22: 5 | F22: 开仓 | G22: 4 | H22: 2757 | I22: 2550.21 | J22: 2 | K22: ¼凯利超上限，取2%
A23: 2021-08-16 | B23: PVC | C23: 多 | D23: 2 | E23: 4 | F23: 开仓 | G23: 8 | H23: 9330 | I23: 8850 | J23: 2 | K23: ¼凯利超上限，取2%
A24: 2021-08-16 | B24: 棉花 | C24: 多 | D24: 2 | E24: 4 | F24: 开仓 | G24: 4 | H24: 18145 | I24: 17282.5 | J24: 2 | K24: ¼凯利超上限，取2%
A25: 2021-08-17 | B25: 棕榈油 | C25: 多 | D25: 3 | E25: 7 | F25: 开仓 | G25: 2 | H25: 8418 | I25: 7653 | J25: 2 | K25: ¼凯利超上限，取2%
A26: 2021-08-17 | B26: 豆油 | C26: 多 | D26: 3 | E26: 7 | F26: 开仓 | G26: 1 | H26: 9188 | I26: 8610.29 | J26: 1 | K26: 与棕榈油高度相关（同组≤3%），预算缩小
A27: 2021-08-17 | B27: 沪铝 | C27: 多 | D27: 3 | E27: 6 | F27: 开仓 | G27: 4 | H27: 20515 | I27: 19658.93 | J27: 2 | K27: ¼凯利超上限，取2%
A28: 2021-08-17 | B28: PVC | C28: 多 | D28: 3 | E28: 6 | F28: 续持 | G28: 8 | H28: 9450 | I28: 8990.36 | J28: 2 | K28: 续持原仓（2021-08-16开）
A29: 2021-08-17 | B29: 玉米 | C29: 多 | D29: 3 | E29: 6 | F29: 不做 | H29: 2593 | J29: 0 | K29: 组合风险已近10%，预算缩小
A30: 2021-08-18 | B30: 棉花 | C30: 多 | D30: 3 | E30: 6 | F30: 续持 | G30: 4 | H30: 18290 | I30: 17594.29 | J30: 2 | K30: 续持原仓（2021-08-16开）
A31: 2021-08-18 | B31: 聚丙烯 | C31: 空 | D31: 2 | E31: 5 | F31: 观望 | G31: 4 | H31: 8482 | I31: 8863.21 | J31: 0.94 | K31: 逆5日线（收盘在5日线上，不追空）
A32: 2021-08-18 | B32: 沪铜 | C32: 空 | D32: 2 | E32: 4 | F32: 不做 | H32: 68720 | J32: 0.94 | K32: 1手风险16243元超过预算9400元
A33: 2021-08-19 | B33: 豆油 | C33: 多 | D33: 3 | E33: 6 | F33: 观望 | G33: 3 | H33: 9024 | I33: 8411.14 | J33: 2 | K33: 逆5日线（收盘在5日线下，不追多）
A34: 2021-08-19 | B34: 沪镍 | C34: 空 | D34: 2 | E34: 5 | F34: 开仓 | G34: 2 | H34: 141220 | I34: 151137.14 | J34: 2 | K34: ¼凯利超上限，取2%
A35: 2021-08-19 | B35: 聚丙烯 | C35: 空 | D35: 2 | E35: 4 | F35: 开仓 | G35: 9 | H35: 8271 | I35: 8678.57 | J35: 2 | K35: ¼凯利超上限，取2%
A36: 2021-08-19 | B36: PVC | C36: 多 | D36: 2 | E36: 4 | F36: 观望 | G36: 3 | H36: 9140 | I36: 8633.21 | J36: 1 | K36: 逆5日线（收盘在5日线下，不追多）
A37: 2021-08-20 | B37: 纯碱 | C37: 多 | D37: 3 | E37: 6 | F37: 开仓 | G37: 2 | H37: 2742 | I37: 2523.21 | J37: 1.27 | K37: ¼凯利
A38: 2021-08-20 | B38: PVC | C38: 多 | D38: 2 | E38: 4 | F38: 观望 | G38: 4 | H38: 9135 | I38: 8661.43 | J38: 1 | K38: 逆5日线（收盘在5日线下，不追多）
A39: 2021-08-23 | B39: 棕榈油 | C39: 多 | D39: 3 | E39: 7 | F39: 观望 | G39: 1 | H39: 8084 | I39: 7299.71 | J39: 1.27 | K39: 逆5日线（收盘在5日线下，不追多）
A40: 2021-08-23 | B40: 沪铝 | C40: 多 | D40: 3 | E40: 6 | F40: 续持 | G40: 4 | H40: 20390 | I40: 19603.93 | J40: 2 | K40: 续持原仓（2021-08-17开）
A41: 2021-08-23 | B41: 甲醇 | C41: 多 | D41: 2 | E41: 5 | F41: 开仓 | G41: 6 | H41: 2921 | I41: 2735.43 | J41: 1.27 | K41: ¼凯利
A42: 2021-08-23 | B42: PVC | C42: 多 | D42: 2 | E42: 4 | F42: 观望 | G42: 4 | H42: 9130 | I42: 8646.79 | J42: 1 | K42: 逆5日线（收盘在5日线下，不追多）
A43: 2021-08-23 | B43: 聚丙烯 | C43: 多 | D43: 2 | E43: 4 | F43: 观望 | G43: 6 | H43: 8315 | I43: 7928.43 | J43: 1.27 | K43: 逆5日线（收盘在5日线下，不追多）
A44: 2021-08-24 | B44: 棕榈油 | C44: 多 | D44: 3 | E44: 6 | F44: 影子仓 | G44: 1 | H44: 8168 | I44: 7421.43 | J44: 1 | K44: 凯利≤0，开1%影子仓（只统计，不计入组合）
... A70: 2021-09-02 | B70: 白糖 | C70: 多 | D70: 2 | E70: 4 | F70: 影子仓 | G70: 4 | H70: 5884 | I70: 5679.14 | J70: 1 | K70: 凯利≤0，开1%影子仓（只统计，不计入组合）
A71: 2021-09-03 | B71: 沪金 | C71: 多 | D71: 2 | E71: 4 | F71: 观望 | H71: 378.54 | J71: 1 | K71: 逆5日线（收盘在5日线下，不追多）
A72: 2021-09-03 | B72: 沪镍 | C72: 空 | D72: 2 | E72: 4 | F72: 影子仓 | G72: 1 | H72: 145540 | I72: 154655.71 | J72: 1 | K72: 凯利≤0，开1%影子仓（只统计，不计入组合）
A73: 2021-09-03 | B73: 白糖 | C73: 多 | D73: 2 | E73: 4 | F73: 续持 | G73: 4 | H73: 5913 | I73: 5726.5 | J73: 1 | K73: 续持原仓（2021-09-02开）
A74: 2021-09-06 | B74: 沪锌 | C74: 空 | D74: 2 | E74: 4 | F74: 观望 | G74: 2 | H74: 22585 | I74: 23467.86 | J74: 1 | K74: 逆5日线（收盘在5日线上，不追空）
A75: 2021-09-07 | B75: 甲醇 | C75: 多 | D75: 3 | E75: 7 | F75: 开仓 | G75: 8 | H75: 3052 | I75: 2825.71 | J75: 2 | K75: ¼凯利超上限，取2%
A76: 2021-09-07 | B76: 玉米 | C76: 空 | D76: 3 | E76: 6 | F76: 开仓 | G76: 24 | H76: 2462 | I76: 2542.36 | J76: 2 | K76: ¼凯利超上限，取2%
A77: 2021-09-07 | B77: 沪锌 | C77: 空 | D77: 2 | E77: 5 | F77: 观望 | G77: 4 | H77: 22505 | I77: 23370.71 | J77: 2 | K77: 逆5日线（收盘在5日线上，不追空）
A78: 2021-09-07 | B78: PTA | C78: 空 | D78: 2 | E78: 4 | F78: 观望 | G78: 12 | H78: 4914 | I78: 5240.14 | J78: 2 | K78: 逆5日线（收盘在5日线上，不追空）
A79: 2021-09-08 | B79: 甲醇 | C79: 多 | D79: 3 | E79: 6 | F79: 续持 | G79: 8 | H79: 3059 | I79: 2850.57 | J79: 2 | K79: 续持原仓（2021-09-07开）
A80: 2021-09-08 | B80: 沪锌 | C80: 空 | D80: 2 | E80: 5 | F80: 观望 | G80: 4 | H80: 22630 | I80: 23488.21 | J80: 2 | K80: 逆5日线（收盘在5日线上，不追空）
A81: 2021-09-08 | B81: 棉花 | C81: 多 | D81: 2 | E81: 4 | F81: 开仓 | G81: 3 | H81: 18085 | I81: 16997.5 | J81: 2 | K81: ¼凯利超上限，取2%
A82: 2021-09-09 | B82: PVC | C82: 多 | D82: 3 | E82: 7 | F82: 开仓 | G82: 6 | H82: 9885 | I82: 9301.07 | J82: 2 | K82: ¼凯利超上限，取2%
A83: 2021-09-09 | B83: 玉米 | C83: 空 | D83: 3 | E83: 6 | F83: 开仓 | G83: 26 | H83: 2463 | I83: 2538.86 | J83: 2 | K83: ¼凯利超上限，取2%
... A89: 2021-09-10 | B89: PVC | C89: 多 | D89: 3 | E89: 6 | F89: 续持 | G89: 6 | H89: 9915 | I89: 9493.93 | J89: 2 | K89: 续持原仓（2021-09-09开）
A90: 2021-09-10 | B90: 沪锌 | C90: 空 | D90: 2 | E90: 4 | F90: 观望 | H90: 22940 | J90: 0.26 | K90: 逆5日线（收盘在5日线上，不追空）
A91: 2021-09-13 | B91: 玉米 | C91: 空 | D91: 2 | E91: 5 | F91: 观望 | H91: 2477 | J91: 0.26 | K91: 逆5日线（收盘在5日线上，不追空）
A92: 2021-09-14 | B92: 玉米 | C92: 空 | D92: 3 | E92: 6 | F92: 续持 | G92: 26 | H92: 2457 | I92: 2524.07 | J92: 2 | K92: 续持原仓（2021-09-09开）
A93: 2021-09-14 | B93: 聚丙烯 | C93: 多 | D93: 2 | E93: 5 | F93: 不做 | H93: 8602 | J93: 0.26 | K93: ¼凯利
A94: 2021-09-14 | B94: 塑料 | C94: 多 | D94: 2 | E94: 5 | F94: 不做 | H94: 8565 | J94: 0.26 | K94: ¼凯利
A95: 2021-09-15 | B95: 棕榈油 | C95: 多 | D95: 3 | E95: 7 | F95: 开仓 | G95: 2 | H95: 8442 | I95: 7756.29 | J95: 2 | K95: ¼凯利超上限，取2%
A96: 2021-09-15 | B96: 玉米 | C96: 空 | D96: 2 | E96: 5 | F96: 续持 | G96: 26 | H96: 2459 | I96: 2524.07 | J96: 2 | K96: 续持原仓（2021-09-09开）
A97: 2021-09-15 | B97: 塑料 | C97: 多 | D97: 2 | E97: 4 | F97: 不做 | H97: 8980 | J97: 0.26 | K97: ¼凯利
A98: 2021-09-15 | B98: 螺纹钢 | C98: 多 | D98: 2 | E98: 4 | F98: 观望 | H98: 5518 | J98: 0.26 | K98: 逆5日线（收盘在5日线下，不追多）
A99: 2021-09-15 | B99: 沪镍 | C99: 多 | D99: 2 | E99: 4 | F99: 观望 | H99: 146870 | J99: 0.26 | K99: 逆5日线（收盘在5日线下，不追多）
A100: 2021-09-16 | B100: 棕榈油 | C100: 多 | D100: 3 | E100: 7 | F100: 续持 | G100: 2 | H100: 8564 | I100: 7963.71 | J100: 2 | K100: 续持原仓（2021-09-15开）
A101: 2021-09-16 | B101: 玉米 | C101: 空 | D101: 3 | E101: 6 | F101: 续持 | G101: 26 | H101: 2437 | I101: 2510.79 | J101: 2 | K101: 续持原仓（2021-09-09开）
A102: 2021-09-16 | B102: PVC | C102: 多 | D102: 3 | E102: 6 | F102: 开仓 | G102: 5 | H102: 10075 | I102: 9321.79 | J102: 2 | K102: ¼凯利超上限，取2%
A103: 2021-09-16 | B103: 豆粕 | C103: 多 | D103: 2 | E103: 4 | F103: 不做 | H103: 3548 | J103: 0.26 | K103: ¼凯利
A104: 2021-09-16 | B104: 棉花 | C104: 多 | D104: 2 | E104: 4 | F104: 续持 | G104: 3 | H104: 17620 | I104: 17246.43 | J104: 2 | K104: 续持原仓（2021-09-08开）
A105: 2021-09-17 | B105: 玉米 | C105: 空 | D105: 3 | E105: 6 | F105: 续持 | G105: 26 | H105: 2437 | I105: 2507.07 | J105: 2 | K105: 续持原仓（2021-09-09开）
A106: 2021-09-17 | B106: 菜粕 | C106: 多 | D106: 3 | E106: 6 | F106: 开仓 | G106: 13 | H106: 2939 | I106: 2790.71 | J106: 2 | K106: ¼凯利超上限，取2%
A107: 2021-09-17 | B107: 沪铝 | C107: 多 | D107: 2 | E107: 5 | F107: 观望 | H107: 22585 | J107: 0.26 | K107: 逆5日线（收盘在5日线下，不追多）
A108: 2021-09-22 | B108: 沪铝 | C108: 多 | D108: 3 | E108: 6 | F108: 开仓 | G108: 2 | H108: 23080 | I108: 21117.14 | J108: 2 | K108: ¼凯利超上限，取2%
A109: 2021-09-22 | B109: 沪锌 | C109: 空 | D109: 3 | E109: 6 | F109: 观望 | G109: 4 | H109: 22790 | I109: 23688.93 | J109: 2 | K109: 逆5日线（收盘在5日线上，不追空）
A110: 2021-09-22 | B110: 聚丙烯 | C110: 多 | D110: 2 | E110: 5 | F110: 影子仓 | G110: 3 | H110: 9109 | I110: 8517.79 | J110: 1 | K110: 凯利≤0，开1%影子仓（只统计，不计入组合）
A111: 2021-09-22 | B111: PVC | C111: 多 | D111: 2 | E111: 5 | F111: 影子仓 | G111: 2 | H111: 10335 | I111: 9470.36 | J111: 1 | K111: 凯利≤0，开1%影子仓（只统计，不计入组合）
A112: 2021-09-22 | B112: 玉米 | C112: 空 | D112: 2 | E112: 4 | F112: 观望 | G112: 12 | H112: 2463 | I112: 2541 | J112: 1 | K112: 逆5日线（收盘在5日线上，不追空）
A113: 2021-09-22 | B113: 塑料 | C113: 多 | D113: 2 | E113: 4 | F113: 影子仓 | G113: 3 | H113: 8870 | I113: 8234.64 | J113: 1 | K113: 凯利≤0，开1%影子仓（只统计，不计入组合）
A114: 2021-09-22 | B114: 甲醇 | C114: 多 | D114: 2 | E114: 4 | F114: 影子仓 | G114: 3 | H114: 3150 | I114: 2842.5 | J114: 1 | K114: 凯利≤0，开1%影子仓（只统计，不计入组合）
A115: 2021-09-23 | B115: 沪铝 | C115: 多 | D115: 3 | E115: 7 | F115: 续持 | G115: 2 | H115: 23500 | I115: 21570 | J115: 2 | K115: 续持原仓（2021-09-22开）
A116: 2021-09-23 | B116: 沪镍 | C116: 多 | D116: 2 | E116: 4 | F116: 开仓 | G116: 1 | H116: 145590 | I116: 133643.57 | J116: 2 | K116: ¼凯利超上限，取2%
A117: 2021-09-23 | B117: 沪金 | C117: 空 | D117: 2 | E117: 4 | F117: 开仓 | G117: 1 | H117: 369.26 | I117: 381.29 | J117: 2 | K117: ¼凯利超上限，取2%
A118: 2021-09-23 | B118: 菜粕 | C118: 多 | D118: 2 | E118: 4 | F118: 观望 | H118: 2901 | J118: 0 | K118: 逆5日线（收盘在5日线下，不追多）
A119: 2021-09-23 | B119: 铁矿石 | C119: 空 | D119: 2 | E119: 4 | F119: 观望 | H119: 667 | J119: 0 | K119: 逆5日线（收盘在5日线上，不追空）
A120: 2021-09-24 | B120: 棕榈油 | C120: 多 | D120: 3 | E120: 6 | F120: 开仓 | G120: 2 | H120: 8706 | I120: 7929.43 | J120: 2 | K120: ¼凯利超上限，取2%
A121: 2021-09-24 | B121: 塑料 | C121: 多 | D121: 3 | E121: 6 | F121: 不做 | H121: 9035 | J121: 0 | K121: 组合风险已近10%，预算缩小
A122: 2021-09-24 | B122: PVC | C122: 多 | D122: 3 | E122: 6 | F122: 不做 | H122: 10565 | J122: 0 | K122: 组合风险已近10%，预算缩小
A123: 2021-09-24 | B123: 沪金 | C123: 空 | D123: 3 | E123: 6 | F123: 续持 | G123: 1 | H123: 366.78 | I123: 377.36 | J123: 2 | K123: 续持原仓（2021-09-23开）
A124: 2021-09-24 | B124: 沪镍 | C124: 多 | D124: 2 | E124: 5 | F124: 续持 | G124: 1 | H124: 144500 | I124: 134480.71 | J124: 2 | K124: 续持原仓（2021-09-23开）
A125: 2021-09-27 | B125: 沪金 | C125: 空 | D125: 2 | E125: 5 | F125: 续持 | G125: 1 | H125: 367.86 | I125: 376.91 | J125: 2 | K125: 续持原仓（2021-09-23开）
A126: 2021-09-27 | B126: 沪锌 | C126: 空 | D126: 2 | E126: 5 | F126: 观望 | G126: 4 | H126: 23020 | I126: 23954.29 | J126: 2 | K126: 逆5日线（收盘在5日线上，不追空）
A127: 2021-09-28 | B127: 燃料油 | C127: 多 | D127: 3 | E127: 7 | F127: 开仓 | G127: 7 | H127: 3108 | I127: 2851.5 | J127: 2 | K127: ¼凯利超上限，取2%
A128: 2021-09-28 | B128: 棕榈油 | C128: 多 | D128: 3 | E128: 6 | F128: 不做 | H128: 8650 | J128: 0 | K128: 组合风险已近10%，预算缩小
A129: 2021-09-28 | B129: 沪铝 | C129: 多 | D129: 3 | E129: 6 | F129: 观望 | H129: 22680 | J129: 0 | K129: 逆5日线（收盘在5日线下，不追多）
A130: 2021-09-28 | B130: 沪金 | C130: 空 | D130: 3 | E130: 6 | F130: 续持 | G130: 1 | H130: 364.22 | I130: 376.6 | J130: 2 | K130: 续持原仓（2021-09-23开）
...
